CMakeLists.txt
COPYING_CECILL_B.LIB
COPYING_CECILL_C.LIB
COPYING_CECILL_V2.1.LIB
LICENSE
MANIFEST.in
README.pypi
README.rst
pyproject.toml
setup.py
setup.py.in
calcephpy.egg-info/PKG-INFO
calcephpy.egg-info/SOURCES.txt
calcephpy.egg-info/dependency_links.txt
calcephpy.egg-info/requires.txt
calcephpy.egg-info/top_level.txt
doc/CMakeLists.txt
doc/man1/CMakeLists.txt
doc/man1/calceph_inspector.1.in
doc/man1/calceph_queryorientation.1.in
doc/man1/calceph_queryposition.1.in
doc/source/arg_PV.rst
doc/source/arg_PVAJ_order.rst
doc/source/arg_PVAJ_orient_order.rst
doc/source/arg_PVAJ_rotangmom_order.rst
doc/source/arg_PV_orient_unit.rst
doc/source/arg_PV_rotangmom_unit.rst
doc/source/arg_PV_unit.rst
doc/source/arg_order.rst
doc/source/arg_order_orient.rst
doc/source/arg_order_rotangmom.rst
doc/source/arg_orientrecordindex.rst
doc/source/arg_orientrecordindex2.rst
doc/source/arg_positionrecordindex.rst
doc/source/arg_positionrecordindex2.rst
doc/source/arg_unit.rst
doc/source/arg_unit_idbyname.rst
doc/source/arg_unit_order.rst
doc/source/arg_unit_orient_unit.rst
doc/source/calceph.copying.rst
doc/source/calceph.error.cusage.rst
doc/source/calceph.error.f2003usage.rst
doc/source/calceph.error.f9xusage.rst
doc/source/calceph.error.mexusage.rst
doc/source/calceph.error.pythonusage.rst
doc/source/calceph.error.rst
doc/source/calceph.final.rst
doc/source/calceph.install.cusage.rst
doc/source/calceph.install.mexusage.rst
doc/source/calceph.install.pythonusage.rst
doc/source/calceph.interface.cusage.rst
doc/source/calceph.interface.f2003usage.rst
doc/source/calceph.interface.f9xusage.rst
doc/source/calceph.interface.mexusage.rst
doc/source/calceph.interface.pythonusage.rst
doc/source/calceph.intro.rst
doc/source/calceph.misc.cusage.rst
doc/source/calceph.misc.f2003usage.rst
doc/source/calceph.misc.f9xusage.rst
doc/source/calceph.misc.mexusage.rst
doc/source/calceph.misc.pythonusage.rst
doc/source/calceph.multiple.cusage.rst
doc/source/calceph.multiple.f2003usage.rst
doc/source/calceph.multiple.f9xusage.rst
doc/source/calceph.multiple.mexusage.rst
doc/source/calceph.multiple.pythonusage.rst
doc/source/calceph.multiple_compute.rst
