Metadata-Version: 1.1
Name: calcephpy
Version: 4.0.5
Summary: Python interface for the CALCEPH Library
Home-page: https://www.imcce.fr/inpop/calceph/
Author: Mickael Gastineau
Author-email: inpop.imcce@obspm.fr
License: CeCILL-C or CeCILL-B or CeCILL v2.1
Platform: UNKNOWN
Classifier: Topic :: Scientific/Engineering :: Astronomy
Classifier: Topic :: Software Development :: Libraries
